lazyarray.py
lazyarray-0.7.0.dist-info/licenses/LICENSE
lazyarray-0.7.0.dist-info/METADATA
lazyarray-0.7.0.dist-info/WHEEL
lazyarray-0.7.0.dist-info/top_level.txt
lazyarray-0.7.0.dist-info/RECORD
