Metadata-Version: 2.4
Name: lazyarray
Version: 0.7.0
Summary: A Python package that provides a lazily-evaluated numerical array class, larray, based on and compatible with NumPy arrays.
Author-email: "Andrew P. Davison" <andrew.davison@cnrs.fr>
Maintainer-email: "Andrew P. Davison" <andrew.davison@cnrs.fr>
License-Expression: BSD-3-Clause
Project-URL: homepage, https://github.com/NeuralEnsemble/lazyarray/
Project-URL: documentation, https://lazyarray.readthedocs.io/
Project-URL: repository, https://github.com/NeuralEnsemble/lazyarray/
Project-URL: changelog, https://github.com/NeuralEnsemble/lazyarray/blob/master/changelog.txt
Project-URL: download, http://pypi.python.org/pypi/lazyarray
Keywords: lazy evaluation, array
Classifier: Development Status :: 4 - Beta
Classifier: Intended Audience :: Science/Research
Classifier: Natural Language :: English
Classifier: Operating System :: OS Independent
Classifier: Programming Language :: Python :: 3
Classifier: Topic :: Scientific/Engineering
Requires-Python: >=3.10
License-File: LICENSE
Requires-Dist: numpy>=1.23.5
Provides-Extra: sparse
Requires-Dist: scipy>=1.9.3; extra == "sparse"
Provides-Extra: dev
Requires-Dist: sphinx; extra == "dev"
Requires-Dist: pytest; extra == "dev"
Requires-Dist: pytest-cov; extra == "dev"
Requires-Dist: flake8; extra == "dev"
Requires-Dist: wheel; extra == "dev"
Dynamic: license-file
